beditor/__init__.py
beditor/configure.py
beditor/gui.py
beditor/output.py
beditor/pipeline.py
beditor/data/64_1_1_all_nuclear.cusp.txt
beditor/data/dbepams.tsv
beditor/data/dspecies.tsv
beditor/data/dsubmap_homo_sapiens.csv
beditor/data/dsubmap_saccharomyces_cerevisiae.csv
beditor/data/gui/guiload.gif
beditor/lib/__init__.py
beditor/lib/get_mutations.py
beditor/lib/get_scores.py
beditor/lib/get_seq.py
beditor/lib/get_specificity.py
beditor/lib/global_vars.py
beditor/lib/io_dfs.py
beditor/lib/io_nums.py
beditor/lib/io_seqs.py
beditor/lib/io_strs.py
beditor/lib/io_sys.py
beditor/lib/make_guides.py
beditor/lib/plot_res.py
beditor-1.1.9.dist-info/LICENSE
beditor-1.1.9.dist-info/METADATA
beditor-1.1.9.dist-info/WHEEL
beditor-1.1.9.dist-info/entry_points.txt
beditor-1.1.9.dist-info/top_level.txt
beditor-1.1.9.dist-info/RECORD
