Metadata-Version: 2.1
Name: beditor
Version: 1.1.9
Summary: A computational workflow for designing libraries of guide RNAs for CRISPR base editing
Home-page: https://github.com/rraadd88/beditor
Author: Rohan Dandage
Author-email: rraadd8888@gmail.com, rohan.dandage.1@ulaval.ca
License: General Public License v. 3
Download-URL: https://github.com/rraadd88/beditor/archive/master.zip
Keywords: CRISPR,genome,biology
Platform: Tested on Ubuntu 16.04 64bit
Requires-Dist: biopython (==1.71)
Requires-Dist: regex (==2018.7.11)
Requires-Dist: pandas (==0.23.3)
Requires-Dist: numpy (==1.13.1)
Requires-Dist: matplotlib (==2.2.2)
Requires-Dist: pysam (==0.14.1)
Requires-Dist: requests (==2.19.1)
Requires-Dist: scipy (==1.1.0)
Requires-Dist: tqdm (==4.23.4)
Requires-Dist: seaborn (==0.8.1)
Requires-Dist: datacache (==1.1.4)
Requires-Dist: dna-features-viewer (==0.1.9)
